{
    "all": {
        "GIH WR": {
            "mean": 0.545167279000524,
            "stdev": 0.0397521027381024
        },
        "OH WR": {
            "mean": 0.5363816600114675,
            "stdev": 0.04249032907873995
        },
        "GD WR": {
            "mean": 0.555006375226714,
            "stdev": 0.037148216946350045
        },
        "IWD": {
            "mean": 0.025782487923764787,
            "stdev": 0.03490256038854339
        }
    },
    "WU": {
        "GIH WR": {
            "mean": 0.5335325211308998,
            "stdev": 0.032347683073788845
        },
        "OH WR": {
            "mean": 0.5182634863477542,
            "stdev": 0.031077548196308414
        },
        "GD WR": {
            "mean": 0.5442730220825769,
            "stdev": 0.034423870099554686
        },
        "IWD": {
            "mean": 0.034389821376765904,
            "stdev": 0.03184319406396581
        }
    },
    "WB": {
        "GIH WR": {
            "mean": 0.5672956864681176,
            "stdev": 0.03098649320904156
        },
        "OH WR": {
            "mean": 0.560155634287543,
            "stdev": 0.035001663648015255
        },
        "GD WR": {
            "mean": 0.5767889496064044,
            "stdev": 0.030440945958191353
        },
        "IWD": {
            "mean": 0.026502416437966643,
            "stdev": 0.02864795538664127
        }
    },
    "WR": {
        "GIH WR": {
            "mean": 0.5477400147041293,
            "stdev": 0.035011094500557796
        },
        "OH WR": {
            "mean": 0.5538395366138466,
            "stdev": 0.03449786765508276
        },
        "GD WR": {
            "mean": 0.5469581135779045,
            "stdev": 0.03294246063531502
        },
        "IWD": {
            "mean": -0.002179981217547164,
            "stdev": 0.03407496358736135
        }
    },
    "WG": {
        "GIH WR": {
            "mean": 0.5694004357765665,
            "stdev": 0.03707795700848769
        },
        "OH WR": {
            "mean": 0.5729178392786319,
            "stdev": 0.04109310053246432
        },
        "GD WR": {
            "mean": 0.5710830927428389,
            "stdev": 0.03889482533521205
        },
        "IWD": {
            "mean": 0.006382399818797674,
            "stdev": 0.035307588314422655
        }
    },
    "UB": {
        "GIH WR": {
            "mean": 0.5584846490087174,
            "stdev": 0.035721016804050466
        },
        "OH WR": {
            "mean": 0.5321585293348589,
            "stdev": 0.03982540387419228
        },
        "GD WR": {
            "mean": 0.5735559841951238,
            "stdev": 0.03690238899440277
        },
        "IWD": {
            "mean": 0.056226227107950534,
            "stdev": 0.03530397451749993
        }
    },
    "UR": {
        "GIH WR": {
            "mean": 0.5224767424668751,
            "stdev": 0.032251226691623516
        },
        "OH WR": {
            "mean": 0.5066158719150381,
            "stdev": 0.03586548125116573
        },
        "GD WR": {
            "mean": 0.534084528729394,
            "stdev": 0.033233349252570425
        },
        "IWD": {
            "mean": 0.03834809074135896,
            "stdev": 0.030973968400442083
        }
    },
    "UG": {
        "GIH WR": {
            "mean": 0.5557769951604344,
            "stdev": 0.038094243260503105
        },
        "OH WR": {
            "mean": 0.5436043893141398,
            "stdev": 0.04079429109979567
        },
        "GD WR": {
            "mean": 0.5633149961135666,
            "stdev": 0.039116105827610895
        },
        "IWD": {
            "mean": 0.03307607226242564,
            "stdev": 0.039273059136892746
        }
    },
    "BR": {
        "GIH WR": {
            "mean": 0.532692667087989,
            "stdev": 0.033586850944364345
        },
        "OH WR": {
            "mean": 0.5281915016983665,
            "stdev": 0.03911870310123295
        },
        "GD WR": {
            "mean": 0.5372429137540832,
            "stdev": 0.033340558276940005
        },
        "IWD": {
            "mean": 0.014380000813147406,
            "stdev": 0.03321606598453327
        }
    },
    "BG": {
        "GIH WR": {
            "mean": 0.5707373249146108,
            "stdev": 0.03829936508873926
        },
        "OH WR": {
            "mean": 0.5633056344571398,
            "stdev": 0.0411574661014557
        },
        "GD WR": {
            "mean": 0.5810708784397925,
            "stdev": 0.03852258191676625
        },
        "IWD": {
            "mean": 0.03244155073190992,
            "stdev": 0.03966871589184709
        }
    },
    "RG": {
        "GIH WR": {
            "mean": 0.5522167611294293,
            "stdev": 0.03639310681303327
        },
        "OH WR": {
            "mean": 0.5561585249226152,
            "stdev": 0.04118935208321768
        },
        "GD WR": {
            "mean": 0.5507247667667485,
            "stdev": 0.03948249631977509
        },
        "IWD": {
            "mean": 0.004148983800452082,
            "stdev": 0.039071632666208625
        }
    }
}