{
    "all": {
        "GIH WR": {
            "mean": 0.5533200066227942,
            "stdev": 0.038117110477260574
        },
        "OH WR": {
            "mean": 0.5521659120969806,
            "stdev": 0.04071453172601705
        },
        "GD WR": {
            "mean": 0.560661351640508,
            "stdev": 0.03438004274949192
        },
        "IWD": {
            "mean": 0.01225015048323561,
            "stdev": 0.03592354966948827
        }
    },
    "WU": {
        "GIH WR": {
            "mean": 0.5875082071689844,
            "stdev": 0.023944164335521677
        },
        "OH WR": {
            "mean": 0.6049392635906227,
            "stdev": 0.020819549834701096
        },
        "GD WR": {
            "mean": 0.5916375382141214,
            "stdev": 0.031671307681258185
        },
        "IWD": {
            "mean": 0.006017959433129338,
            "stdev": 0.022887708925202196
        }
    },
    "WB": {
        "GIH WR": {
            "mean": 0.5433243103994884,
            "stdev": 0.02473048212175204
        },
        "OH WR": {
            "mean": 0.5466970372008396,
            "stdev": 0.028171104059497784
        },
        "GD WR": {
            "mean": 0.5420960399889613,
            "stdev": 0.025787035913456702
        },
        "IWD": {
            "mean": 0.0060492130069303195,
            "stdev": 0.025149032159251815
        }
    },
    "WR": {
        "GIH WR": {
            "mean": 0.5892090073803367,
            "stdev": 0.03562443504219632
        },
        "OH WR": {
            "mean": 0.6080586004810785,
            "stdev": 0.032376768915149894
        },
        "GD WR": {
            "mean": 0.578039886021562,
            "stdev": 0.027127697987896732
        },
        "IWD": {
            "mean": -0.01657402604624775,
            "stdev": 0.0349277061978443
        }
    },
    "WG": {
        "GIH WR": {
            "mean": 0.5611880545156814,
            "stdev": 0.02441397850235167
        },
        "OH WR": {
            "mean": 0.5756662384077674,
            "stdev": 0.03712782887396664
        },
        "GD WR": {
            "mean": 0.55545892541652,
            "stdev": 0.02361669210082732
        },
        "IWD": {
            "mean": -0.012666541203271325,
            "stdev": 0.026849751478153567
        }
    },
    "UB": {
        "GIH WR": {
            "mean": 0.5733170062765635,
            "stdev": 0.03215498028819016
        },
        "OH WR": {
            "mean": 0.558398755475766,
            "stdev": 0.03489174354169216
        },
        "GD WR": {
            "mean": 0.5912447814401975,
            "stdev": 0.035962933858933815
        },
        "IWD": {
            "mean": 0.059248462222071974,
            "stdev": 0.03824814034143291
        }
    },
    "UR": {
        "GIH WR": {
            "mean": 0.5639195273388338,
            "stdev": 0.027099387753021783
        },
        "OH WR": {
            "mean": 0.5564923474096845,
            "stdev": 0.02618214130213853
        },
        "GD WR": {
            "mean": 0.5787760536151586,
            "stdev": 0.02458322845367233
        },
        "IWD": {
            "mean": 0.03372064775867822,
            "stdev": 0.03184893907409517
        }
    },
    "UG": {
        "GIH WR": {
            "mean": 0.5662099154509322,
            "stdev": 0.0313167957097876
        },
        "OH WR": {
            "mean": 0.5554239575341242,
            "stdev": 0.03405577714545078
        },
        "GD WR": {
            "mean": 0.5766112211468359,
            "stdev": 0.027680558254170304
        },
        "IWD": {
            "mean": 0.03680890372581387,
            "stdev": 0.0327813761772597
        }
    },
    "BR": {
        "GIH WR": {
            "mean": 0.5476627006896126,
            "stdev": 0.036508377392976105
        },
        "OH WR": {
            "mean": 0.5546441956130371,
            "stdev": 0.03914482162621067
        },
        "GD WR": {
            "mean": 0.5576044893981577,
            "stdev": 0.028012612305133164
        },
        "IWD": {
            "mean": 0.005873163693862618,
            "stdev": 0.03667900881170729
        }
    },
    "BG": {
        "GIH WR": {
            "mean": 0.5433715817204133,
            "stdev": 0.03438765997899332
        },
        "OH WR": {
            "mean": 0.5502383619449188,
            "stdev": 0.032348836475600204
        },
        "GD WR": {
            "mean": 0.5519031847343824,
            "stdev": 0.02878246931888667
        },
        "IWD": {
            "mean": 0.007074515190857622,
            "stdev": 0.03562439181971742
        }
    },
    "RG": {
        "GIH WR": {
            "mean": 0.6028824232124933,
            "stdev": 0.0316960686936019
        },
        "OH WR": {
            "mean": 0.6167718101933944,
            "stdev": 0.03165227737204984
        },
        "GD WR": {
            "mean": 0.6116363473544402,
            "stdev": 0.03361785095186257
        },
        "IWD": {
            "mean": -0.002493012697672466,
            "stdev": 0.029942352831984688
        }
    }
}