{
    "all": {
        "GIH WR": {
            "mean": 0.5568291211293347,
            "stdev": 0.03918350115625476
        },
        "OH WR": {
            "mean": 0.554896363736491,
            "stdev": 0.04538568729262213
        },
        "GD WR": {
            "mean": 0.5598561030986208,
            "stdev": 0.03733679541217877
        },
        "IWD": {
            "mean": 0.012312828095349749,
            "stdev": 0.03799290884963559
        }
    },
    "WU": {
        "GIH WR": {
            "mean": 0.554693145442453,
            "stdev": 0.03643843457510638
        },
        "OH WR": {
            "mean": 0.56614216298513,
            "stdev": 0.04034411228857365
        },
        "GD WR": {
            "mean": 0.5562574554222534,
            "stdev": 0.035575729703076646
        },
        "IWD": {
            "mean": -0.00971652341246272,
            "stdev": 0.03531896066179161
        }
    },
    "WB": {
        "GIH WR": {
            "mean": 0.5574062947744918,
            "stdev": 0.03378093401489791
        },
        "OH WR": {
            "mean": 0.5614120843520523,
            "stdev": 0.035664713988623746
        },
        "GD WR": {
            "mean": 0.5622518383731995,
            "stdev": 0.02924606629593899
        },
        "IWD": {
            "mean": 0.004025727101334612,
            "stdev": 0.033104880120133975
        }
    },
    "WR": {
        "GIH WR": {
            "mean": 0.5849974386809791,
            "stdev": 0.04213804676386813
        },
        "OH WR": {
            "mean": 0.6018675772297647,
            "stdev": 0.039550479695309
        },
        "GD WR": {
            "mean": 0.5839304565817012,
            "stdev": 0.032766209151110046
        },
        "IWD": {
            "mean": -0.01571416201794506,
            "stdev": 0.034773637537982544
        }
    },
    "WG": {
        "GIH WR": {
            "mean": 0.5777640539880939,
            "stdev": 0.04049623500907997
        },
        "OH WR": {
            "mean": 0.584579928591178,
            "stdev": 0.035718177917190314
        },
        "GD WR": {
            "mean": 0.5821876876667688,
            "stdev": 0.030525741496149814
        },
        "IWD": {
            "mean": -0.004258031896439876,
            "stdev": 0.03709594482137052
        }
    },
    "UB": {
        "GIH WR": {
            "mean": 0.5457059554480085,
            "stdev": 0.03518047208387895
        },
        "OH WR": {
            "mean": 0.5353415180620422,
            "stdev": 0.03813366596177194
        },
        "GD WR": {
            "mean": 0.5498855450280711,
            "stdev": 0.0258689067799105
        },
        "IWD": {
            "mean": 0.028041932289738513,
            "stdev": 0.03950937498714437
        }
    },
    "UR": {
        "GIH WR": {
            "mean": 0.5640763606131178,
            "stdev": 0.030501023755721418
        },
        "OH WR": {
            "mean": 0.5593151929423339,
            "stdev": 0.03201707459165539
        },
        "GD WR": {
            "mean": 0.572282253186852,
            "stdev": 0.027677230688607474
        },
        "IWD": {
            "mean": 0.011223221203252571,
            "stdev": 0.02802334745264487
        }
    },
    "UG": {
        "GIH WR": {
            "mean": 0.5665952680162342,
            "stdev": 0.027306100702072202
        },
        "OH WR": {
            "mean": 0.5612272937212455,
            "stdev": 0.022812855045062877
        },
        "GD WR": {
            "mean": 0.5860041826072516,
            "stdev": 0.028377849269843602
        },
        "IWD": {
            "mean": 0.01535244119036633,
            "stdev": 0.031550954455275886
        }
    },
    "BR": {
        "GIH WR": {
            "mean": 0.5424056733220304,
            "stdev": 0.03054762569818503
        },
        "OH WR": {
            "mean": 0.5432543012927434,
            "stdev": 0.034414547946993605
        },
        "GD WR": {
            "mean": 0.542967021898083,
            "stdev": 0.024933819745116825
        },
        "IWD": {
            "mean": 0.01185249248703409,
            "stdev": 0.03300690189639805
        }
    },
    "BG": {
        "GIH WR": {
            "mean": 0.5524890586640023,
            "stdev": 0.04146891067070291
        },
        "OH WR": {
            "mean": 0.5433303208417434,
            "stdev": 0.03831205023573008
        },
        "GD WR": {
            "mean": 0.564847817016822,
            "stdev": 0.03791407416616429
        },
        "IWD": {
            "mean": 0.03006695526460616,
            "stdev": 0.040523571272988966
        }
    },
    "RG": {
        "GIH WR": {
            "mean": 0.5510156731846677,
            "stdev": 0.0341967688431584
        },
        "OH WR": {
            "mean": 0.5607607448690538,
            "stdev": 0.030969643336474027
        },
        "GD WR": {
            "mean": 0.551240062189871,
            "stdev": 0.030237047579114367
        },
        "IWD": {
            "mean": 0.003405755465794088,
            "stdev": 0.03545361043723333
        }
    }
}