{
    "all": {
        "GIH WR": {
            "mean": 0.5516098298890201,
            "stdev": 0.038733405078040774
        },
        "OH WR": {
            "mean": 0.5464587685205027,
            "stdev": 0.04565362785169398
        },
        "GD WR": {
            "mean": 0.5591148014860496,
            "stdev": 0.0349046272800238
        },
        "IWD": {
            "mean": 0.016785449618954316,
            "stdev": 0.03406542033920884
        }
    },
    "WU": {
        "GIH WR": {
            "mean": 0.5284885685238915,
            "stdev": 0.035091287727702786
        },
        "OH WR": {
            "mean": 0.5058255182979514,
            "stdev": 0.03764745734439453
        },
        "GD WR": {
            "mean": 0.5386527670655599,
            "stdev": 0.03157027264042113
        },
        "IWD": {
            "mean": 0.04350970862682922,
            "stdev": 0.035896748406503726
        }
    },
    "WB": {
        "GIH WR": {
            "mean": 0.5434545396646405,
            "stdev": 0.03950615707985723
        },
        "OH WR": {
            "mean": 0.5412509367156835,
            "stdev": 0.042017443384782825
        },
        "GD WR": {
            "mean": 0.5499537526420759,
            "stdev": 0.036234656053157226
        },
        "IWD": {
            "mean": 0.016888415092305178,
            "stdev": 0.03665816243311468
        }
    },
    "WR": {
        "GIH WR": {
            "mean": 0.5592387993901973,
            "stdev": 0.040584208696968695
        },
        "OH WR": {
            "mean": 0.5726409653434659,
            "stdev": 0.04162799542523301
        },
        "GD WR": {
            "mean": 0.5560811191472702,
            "stdev": 0.0394325717566309
        },
        "IWD": {
            "mean": -0.011712586999428625,
            "stdev": 0.03316652526627703
        }
    },
    "WG": {
        "GIH WR": {
            "mean": 0.5499018680232758,
            "stdev": 0.03421750350936925
        },
        "OH WR": {
            "mean": 0.5470624153192423,
            "stdev": 0.037318745877422455
        },
        "GD WR": {
            "mean": 0.5535435735666379,
            "stdev": 0.037896857970818855
        },
        "IWD": {
            "mean": 0.018565971264862237,
            "stdev": 0.03370957529038482
        }
    },
    "UB": {
        "GIH WR": {
            "mean": 0.5569960857952233,
            "stdev": 0.037480126037764724
        },
        "OH WR": {
            "mean": 0.5356625893003214,
            "stdev": 0.044541434198022666
        },
        "GD WR": {
            "mean": 0.5707524997527529,
            "stdev": 0.03402249584306422
        },
        "IWD": {
            "mean": 0.040656386726730845,
            "stdev": 0.03543279899907692
        }
    },
    "UR": {
        "GIH WR": {
            "mean": 0.5614706867912803,
            "stdev": 0.03289222699360838
        },
        "OH WR": {
            "mean": 0.5446762196711361,
            "stdev": 0.03846626353244589
        },
        "GD WR": {
            "mean": 0.5751754519044446,
            "stdev": 0.03232619568355457
        },
        "IWD": {
            "mean": 0.04203904587043613,
            "stdev": 0.028916635335343412
        }
    },
    "UG": {
        "GIH WR": {
            "mean": 0.5446980440674951,
            "stdev": 0.03916662757575383
        },
        "OH WR": {
            "mean": 0.5259089872209033,
            "stdev": 0.044329953153758615
        },
        "GD WR": {
            "mean": 0.5601808085876163,
            "stdev": 0.03463633959767897
        },
        "IWD": {
            "mean": 0.045970873434673536,
            "stdev": 0.03696495269472424
        }
    },
    "BR": {
        "GIH WR": {
            "mean": 0.5691083532078018,
            "stdev": 0.038180843714656604
        },
        "OH WR": {
            "mean": 0.5730148552728679,
            "stdev": 0.040405981811070434
        },
        "GD WR": {
            "mean": 0.5693866013584188,
            "stdev": 0.038958727004791485
        },
        "IWD": {
            "mean": 0.0003972880218543608,
            "stdev": 0.03322843115043684
        }
    },
    "BG": {
        "GIH WR": {
            "mean": 0.5693547633777205,
            "stdev": 0.03535526491814682
        },
        "OH WR": {
            "mean": 0.5675007859651754,
            "stdev": 0.041617923790695316
        },
        "GD WR": {
            "mean": 0.573894255879537,
            "stdev": 0.03333821263958173
        },
        "IWD": {
            "mean": 0.012222852644083319,
            "stdev": 0.03503199152054743
        }
    },
    "RG": {
        "GIH WR": {
            "mean": 0.5611921154243323,
            "stdev": 0.03422305904530338
        },
        "OH WR": {
            "mean": 0.5679059313999669,
            "stdev": 0.038559539762778844
        },
        "GD WR": {
            "mean": 0.5633899150320851,
            "stdev": 0.03634664846276766
        },
        "IWD": {
            "mean": 0.002476998217061476,
            "stdev": 0.03299885665969848
        }
    }
}