{
    "all": {
        "GIH WR": {
            "mean": 0.5978618523237171,
            "stdev": 0.03363250367099184
        },
        "OH WR": {
            "mean": 0.6015709756255865,
            "stdev": 0.03279450055460082
        },
        "GD WR": {
            "mean": 0.6054189113151944,
            "stdev": 0.032586128610744704
        },
        "IWD": {
            "mean": 0.019906141370712324,
            "stdev": 0.03238274953848364
        }
    },
    "WU": {
        "GIH WR": {
            "mean": null,
            "stdev": null
        },
        "OH WR": {
            "mean": null,
            "stdev": null
        },
        "GD WR": {
            "mean": null,
            "stdev": null
        },
        "IWD": {
            "mean": null,
            "stdev": null
        }
    },
    "WB": {
        "GIH WR": {
            "mean": null,
            "stdev": null
        },
        "OH WR": {
            "mean": null,
            "stdev": null
        },
        "GD WR": {
            "mean": null,
            "stdev": null
        },
        "IWD": {
            "mean": null,
            "stdev": null
        }
    },
    "WR": {
        "GIH WR": {
            "mean": null,
            "stdev": null
        },
        "OH WR": {
            "mean": null,
            "stdev": null
        },
        "GD WR": {
            "mean": null,
            "stdev": null
        },
        "IWD": {
            "mean": null,
            "stdev": null
        }
    },
    "WG": {
        "GIH WR": {
            "mean": 0.6218350625064603,
            "stdev": 0.02848739698541001
        },
        "OH WR": {
            "mean": 0.6211116777290756,
            "stdev": 0.025137562954244016
        },
        "GD WR": {
            "mean": 0.633553851084109,
            "stdev": 0.03407449716002461
        },
        "IWD": {
            "mean": 0.002826885850154692,
            "stdev": 0.030123403540518384
        }
    },
    "UB": {
        "GIH WR": {
            "mean": 0.6366857087904483,
            "stdev": 0.02011033272365831
        },
        "OH WR": {
            "mean": null,
            "stdev": null
        },
        "GD WR": {
            "mean": null,
            "stdev": null
        },
        "IWD": {
            "mean": 0.055117177485242315,
            "stdev": 0.0257073379756662
        }
    },
    "UR": {
        "GIH WR": {
            "mean": 0.5759558230998965,
            "stdev": 0.016089386738475618
        },
        "OH WR": {
            "mean": null,
            "stdev": null
        },
        "GD WR": {
            "mean": null,
            "stdev": null
        },
        "IWD": {
            "mean": 0.042873802359885735,
            "stdev": 0.027169014705264914
        }
    },
    "UG": {
        "GIH WR": {
            "mean": null,
            "stdev": null
        },
        "OH WR": {
            "mean": null,
            "stdev": null
        },
        "GD WR": {
            "mean": null,
            "stdev": null
        },
        "IWD": {
            "mean": null,
            "stdev": null
        }
    },
    "BR": {
        "GIH WR": {
            "mean": 0.5800502308187528,
            "stdev": 0.03565383024554865
        },
        "OH WR": {
            "mean": null,
            "stdev": null
        },
        "GD WR": {
            "mean": null,
            "stdev": null
        },
        "IWD": {
            "mean": 0.01461238879337347,
            "stdev": 0.03355473708338472
        }
    },
    "BG": {
        "GIH WR": {
            "mean": 0.6276475535760047,
            "stdev": 0.027173095215668776
        },
        "OH WR": {
            "mean": null,
            "stdev": null
        },
        "GD WR": {
            "mean": 0.6407027936988019,
            "stdev": 0.022937323920748088
        },
        "IWD": {
            "mean": 0.02060735645932713,
            "stdev": 0.03585787358234171
        }
    },
    "RG": {
        "GIH WR": {
            "mean": 0.5872370050380439,
            "stdev": 0.02148953529416359
        },
        "OH WR": {
            "mean": null,
            "stdev": null
        },
        "GD WR": {
            "mean": null,
            "stdev": null
        },
        "IWD": {
            "mean": -0.00537499688397215,
            "stdev": 0.024498865601617875
        }
    }
}