{
    "all": {
        "GIH WR": {
            "mean": 0.5954966581636071,
            "stdev": 0.03434725494661333
        },
        "OH WR": {
            "mean": 0.594744941247944,
            "stdev": 0.03624029354095982
        },
        "GD WR": {
            "mean": 0.6020634187351872,
            "stdev": 0.03419841971616018
        },
        "IWD": {
            "mean": 0.013592631353642724,
            "stdev": 0.0383580857376142
        }
    },
    "WU": {
        "GIH WR": {
            "mean": 0.5940465011357596,
            "stdev": 0.029285514120487306
        },
        "OH WR": {
            "mean": 0.5966031212375741,
            "stdev": 0.03456609486661863
        },
        "GD WR": {
            "mean": 0.5916236146975875,
            "stdev": 0.03024430101569837
        },
        "IWD": {
            "mean": -0.003981670536772454,
            "stdev": 0.03365942261189568
        }
    },
    "WB": {
        "GIH WR": {
            "mean": 0.5971928401399643,
            "stdev": 0.02933187514506216
        },
        "OH WR": {
            "mean": 0.5953196623180047,
            "stdev": 0.030321567208895207
        },
        "GD WR": {
            "mean": 0.602726126215474,
            "stdev": 0.02819658309804404
        },
        "IWD": {
            "mean": 0.0003648031489905421,
            "stdev": 0.0348622821833364
        }
    },
    "WR": {
        "GIH WR": {
            "mean": 0.6038026902618623,
            "stdev": 0.03293281887478981
        },
        "OH WR": {
            "mean": 0.6183254316012178,
            "stdev": 0.03332527031010932
        },
        "GD WR": {
            "mean": 0.599430060650926,
            "stdev": 0.03437985788294066
        },
        "IWD": {
            "mean": -0.015523213408836067,
            "stdev": 0.031091019457089256
        }
    },
    "WG": {
        "GIH WR": {
            "mean": 0.6095716539928577,
            "stdev": 0.034526177514126094
        },
        "OH WR": {
            "mean": 0.6052146137013628,
            "stdev": 0.03314442479519647
        },
        "GD WR": {
            "mean": 0.6077496576376287,
            "stdev": 0.029398328532238196
        },
        "IWD": {
            "mean": 0.008582404536754578,
            "stdev": 0.036282033029358965
        }
    },
    "UB": {
        "GIH WR": {
            "mean": 0.5834419957304244,
            "stdev": 0.026294654576568738
        },
        "OH WR": {
            "mean": 0.5759781804902795,
            "stdev": 0.034013489984944745
        },
        "GD WR": {
            "mean": 0.5975939451414228,
            "stdev": 0.025337042166596883
        },
        "IWD": {
            "mean": 0.027329796200057793,
            "stdev": 0.03624134422437396
        }
    },
    "UR": {
        "GIH WR": {
            "mean": 0.5981842562824498,
            "stdev": 0.0305423010684249
        },
        "OH WR": {
            "mean": 0.5949061018803606,
            "stdev": 0.025999720548132828
        },
        "GD WR": {
            "mean": 0.6025604096602509,
            "stdev": 0.03247223388992172
        },
        "IWD": {
            "mean": 0.010475214513719784,
            "stdev": 0.03088001886390236
        }
    },
    "UG": {
        "GIH WR": {
            "mean": 0.6198766898621348,
            "stdev": 0.029230917876581664
        },
        "OH WR": {
            "mean": 0.608636372978079,
            "stdev": 0.03360551627619091
        },
        "GD WR": {
            "mean": 0.6263783410224716,
            "stdev": 0.032381123252401875
        },
        "IWD": {
            "mean": 0.02559586633999898,
            "stdev": 0.032989723397106756
        }
    },
    "BR": {
        "GIH WR": {
            "mean": 0.5870720380397999,
            "stdev": 0.024272589451136375
        },
        "OH WR": {
            "mean": 0.5936945942688003,
            "stdev": 0.0260909440925206
        },
        "GD WR": {
            "mean": 0.5904105443197557,
            "stdev": 0.027744528412868792
        },
        "IWD": {
            "mean": 0.005866368195789412,
            "stdev": 0.0258565828277659
        }
    },
    "BG": {
        "GIH WR": {
            "mean": 0.5991361203322372,
            "stdev": 0.031443012827380296
        },
        "OH WR": {
            "mean": 0.5821188032495271,
            "stdev": 0.03230359325842259
        },
        "GD WR": {
            "mean": 0.6034786311448501,
            "stdev": 0.03244601969347741
        },
        "IWD": {
            "mean": 0.03096318402495948,
            "stdev": 0.03706001568564143
        }
    },
    "RG": {
        "GIH WR": {
            "mean": 0.5898785003427952,
            "stdev": 0.03162613031426499
        },
        "OH WR": {
            "mean": 0.5943601470353119,
            "stdev": 0.024552600384298462
        },
        "GD WR": {
            "mean": 0.5859079914452768,
            "stdev": 0.03189777891310655
        },
        "IWD": {
            "mean": -0.0004332214575475685,
            "stdev": 0.03629960916819163
        }
    }
}