{
    "all": {
        "GIH WR": {
            "mean": 0.6050426745348275,
            "stdev": 0.03615342739485286
        },
        "OH WR": {
            "mean": 0.5976508409006572,
            "stdev": 0.0474943516366456
        },
        "GD WR": {
            "mean": 0.6092344471475541,
            "stdev": 0.033271779300520894
        },
        "IWD": {
            "mean": 0.023900441960068738,
            "stdev": 0.03807470757045201
        }
    },
    "WU": {
        "GIH WR": {
            "mean": 0.6193487650075225,
            "stdev": 0.03616355359938387
        },
        "OH WR": {
            "mean": 0.6135839640389525,
            "stdev": 0.037765195902683006
        },
        "GD WR": {
            "mean": 0.6222975718626667,
            "stdev": 0.03413151666184639
        },
        "IWD": {
            "mean": 0.01699281918692773,
            "stdev": 0.03885435613743135
        }
    },
    "WB": {
        "GIH WR": {
            "mean": 0.5902412834933982,
            "stdev": 0.03486216919378261
        },
        "OH WR": {
            "mean": 0.592195542557194,
            "stdev": 0.03317068782171825
        },
        "GD WR": {
            "mean": 0.6101194889901977,
            "stdev": 0.030191759282200116
        },
        "IWD": {
            "mean": 0.025597979109485244,
            "stdev": 0.03346162349227745
        }
    },
    "WR": {
        "GIH WR": {
            "mean": 0.6005391573463652,
            "stdev": 0.036709956848723684
        },
        "OH WR": {
            "mean": 0.5978180279531573,
            "stdev": 0.031439262344984634
        },
        "GD WR": {
            "mean": 0.5911636275710304,
            "stdev": 0.027186182542213656
        },
        "IWD": {
            "mean": -0.0006484329678123023,
            "stdev": 0.037574584741370466
        }
    },
    "WG": {
        "GIH WR": {
            "mean": 0.6036425411543257,
            "stdev": 0.020830615141195784
        },
        "OH WR": {
            "mean": 0.6041562690638461,
            "stdev": 0.03114844040219987
        },
        "GD WR": {
            "mean": 0.614012249281609,
            "stdev": 0.02179150516183699
        },
        "IWD": {
            "mean": 0.011568669023814575,
            "stdev": 0.022603129793614538
        }
    },
    "UB": {
        "GIH WR": {
            "mean": 0.5958715671106084,
            "stdev": 0.033132607014649505
        },
        "OH WR": {
            "mean": 0.5902493449855306,
            "stdev": 0.03870375451266433
        },
        "GD WR": {
            "mean": 0.6128379192632462,
            "stdev": 0.02967492720099982
        },
        "IWD": {
            "mean": 0.03380004903837721,
            "stdev": 0.03490590188229072
        }
    },
    "UR": {
        "GIH WR": {
            "mean": 0.6164031852536799,
            "stdev": 0.03592870286668575
        },
        "OH WR": {
            "mean": 0.6142583842306544,
            "stdev": 0.03437541087508448
        },
        "GD WR": {
            "mean": 0.6080219651586856,
            "stdev": 0.023414674172172783
        },
        "IWD": {
            "mean": 0.0028312019273921455,
            "stdev": 0.03644216560320945
        }
    },
    "UG": {
        "GIH WR": {
            "mean": 0.5866409249407499,
            "stdev": 0.01994320088601735
        },
        "OH WR": {
            "mean": 0.5851714155831476,
            "stdev": 0.024166173968824634
        },
        "GD WR": {
            "mean": 0.5859638629143238,
            "stdev": 0.021535953748866583
        },
        "IWD": {
            "mean": 0.010588875320219978,
            "stdev": 0.025848824678355944
        }
    },
    "BR": {
        "GIH WR": {
            "mean": 0.5988932479441889,
            "stdev": 0.029903738370726286
        },
        "OH WR": {
            "mean": 0.5981110166495014,
            "stdev": 0.024248200632035803
        },
        "GD WR": {
            "mean": 0.6125741656628422,
            "stdev": 0.018112023992027892
        },
        "IWD": {
            "mean": 0.02645617914584503,
            "stdev": 0.03235930826877949
        }
    },
    "BG": {
        "GIH WR": {
            "mean": 0.606628229623433,
            "stdev": 0.027995581889506068
        },
        "OH WR": {
            "mean": 0.6016139265454461,
            "stdev": 0.03569140214337072
        },
        "GD WR": {
            "mean": 0.6209886783815735,
            "stdev": 0.02676619195807555
        },
        "IWD": {
            "mean": 0.031150139257769126,
            "stdev": 0.028929304538720193
        }
    },
    "RG": {
        "GIH WR": {
            "mean": 0.6133396532319235,
            "stdev": 0.03382772669027785
        },
        "OH WR": {
            "mean": 0.615779077459796,
            "stdev": 0.028256695999696966
        },
        "GD WR": {
            "mean": 0.614954372184732,
            "stdev": 0.031759555200104886
        },
        "IWD": {
            "mean": 0.006005889637809841,
            "stdev": 0.03733536205593355
        }
    }
}